blaze_net/__init__.py
blaze_net/app.py
blaze_net/model_manager.py
blaze_net/routes.py
tests/__init__.py
tests/test_app.py
blaze_net-1.1.1.dist-info/METADATA
blaze_net-1.1.1.dist-info/WHEEL
blaze_net-1.1.1.dist-info/top_level.txt
blaze_net-1.1.1.dist-info/RECORD
