Metadata-Version: 2.1
Name: blaze-net
Version: 1.1.1
Summary: A Python web framework
Home-page: https://github.com/Alan69/blaze_net
Author: McLovinAlan69
Author-email: gameg1676@gmail.com
Classifier: Development Status :: 3 - Alpha
Classifier: License :: OSI Approved :: MIT License
Classifier: Programming Language :: Python :: 3
Classifier: Programming Language :: Python :: 3.6
Classifier: Programming Language :: Python :: 3.7
Classifier: Programming Language :: Python :: 3.8
Classifier: Programming Language :: Python :: 3.9
Classifier: Topic :: Internet :: WWW/HTTP :: Dynamic Content :: CGI Tools/Libraries
Requires-Dist: werkzeug
Requires-Dist: jinja2
Requires-Dist: sqlalchemy
